Timers/__init__.py
Timers/timer.py
GiraffeTimer-0.0.1.dist-info/LICENSE
GiraffeTimer-0.0.1.dist-info/METADATA
GiraffeTimer-0.0.1.dist-info/WHEEL
GiraffeTimer-0.0.1.dist-info/top_level.txt
GiraffeTimer-0.0.1.dist-info/RECORD
