Metadata-Version: 2.1
Name: GiraffeTimer
Version: 0.0.1
Summary: Simple Python Timer
Home-page: https://github.com/Giraffe32/Timer
Author: Elliott D
Author-email: topiatowersofficial@gmail.com
Classifier: Programming Language :: Python :: 3
Classifier: License :: OSI Approved :: MIT License
Classifier: Operating System :: OS Independent
Requires-Python: >=3.7
License-File: LICENSE
